{"ts": 1782253277.8056169, "live": true, "coin": {"symbol": "STARMlND", "label": "STARMlND", "elapsed": 20.75, "dwell": 25.0, "metrics": {"devHold": 1.04, "bundlers": 0, "insiders": 0, "snipers": 1.04, "top10": 1.04, "mcap": 1950, "price": null, "vol": 20.66}, "series": [{"type": "tick", "coin": "STARMlND", "mint": "H38DQyg3LLesk9VSqKASv34y5A7kJBpzWkGpdH7tpump", "label": "STARMlND", "t": 15.9, "wallTs": 1782253272.95, "devHold": 1.04, "bundlers": 0, "insiders": 0, "snipers": 1.04, "top10": 1.04, "mcap": 1940, "price": null, "vol": 20.65}, {"type": "tick", "coin": "STARMlND", "mint": "H38DQyg3LLesk9VSqKASv34y5A7kJBpzWkGpdH7tpump", "label": "STARMlND", "t": 16.02, "wallTs": 1782253273.07, "devHold": 1.04, "bundlers": 0, "insiders": 0, "snipers": 1.04, "top10": 1.04, "mcap": 1940, "price": null, "vol": 20.65}, {"type": "tick", "coin": "STARMlND", "mint": "H38DQyg3LLesk9VSqKASv34y5A7kJBpzWkGpdH7tpump", "label": "STARMlND", "t": 16.14, "wallTs": 1782253273.2, "devHold": 1.04, "bundlers": 0, "insiders": 0, "snipers": 1.04, "top10": 1.04, "mcap": 1940, "price": null, "vol": 20.65}, {"type": "tick", "coin": "STARMlND", "mint": "H38DQyg3LLesk9VSqKASv34y5A7kJBpzWkGpdH7tpump", "label": "STARMlND", "t": 16.27, "wallTs": 1782253273.32, "devHold": 1.04, "bundlers": 0, "insiders": 0, "snipers": 1.04, "top10": 1.04, "mcap": 1940, "price": null, "vol": 20.65}, {"type": "tick", "coin": "STARMlND", "mint": "H38DQyg3LLesk9VSqKASv34y5A7kJBpzWkGpdH7tpump", "label": "STARMlND", "t": 16.39, "wallTs": 1782253273.44, "devHold": 1.04, "bundlers": 0, "insiders": 0, "snipers": 1.04, "top10": 1.04, "mcap": 1940, "price": null, "vol": 20.65}, {"type": "tick", "coin": "STARMlND", "mint": "H38DQyg3LLesk9VSqKASv34y5A7kJBpzWkGpdH7tpump", "label": "STARMlND", "t": 16.51, "wallTs": 1782253273.57, "devHold": 1.04, "bundlers": 0, "insiders": 0, "snipers": 1.04, "top10": 1.04, "mcap": 1940, "price": null, "vol": 20.65}, {"type": "tick", "coin": "STARMlND", "mint": "H38DQyg3LLesk9VSqKASv34y5A7kJBpzWkGpdH7tpump", "label": "STARMlND", "t": 16.64, "wallTs": 1782253273.69, "devHold": 1.04, "bundlers": 0, "insiders": 0, "snipers": 1.04, "top10": 1.04, "mcap": 1940, "price": null, "vol": 20.65}, {"type": "tick", "coin": "STARMlND", "mint": "H38DQyg3LLesk9VSqKASv34y5A7kJBpzWkGpdH7tpump", "label": "STARMlND", "t": 16.76, "wallTs": 1782253273.82, "devHold": 1.04, "bundlers": 0, "insiders": 0, "snipers": 1.04, "top10": 1.04, "mcap": 1940, "price": null, "vol": 20.65}, {"type": "tick", "coin": "STARMlND", "mint": "H38DQyg3LLesk9VSqKASv34y5A7kJBpzWkGpdH7tpump", "label": "STARMlND", "t": 16.89, "wallTs": 1782253273.94, "devHold": 1.04, "bundlers": 0, "insiders": 0, "snipers": 1.04, "top10": 1.04, "mcap": 1940, "price": null, "vol": 20.65}, {"type": "tick", "coin": "STARMlND", "mint": "H38DQyg3LLesk9VSqKASv34y5A7kJBpzWkGpdH7tpump", "label": "STARMlND", "t": 17.01, "wallTs": 1782253274.06, "devHold": 1.04, "bundlers": 0, "insiders": 0, "snipers": 1.04, "top10": 1.04, "mcap": 1940, "price": null, "vol": 20.65}, {"type": "tick", "coin": "STARMlND", "mint": "H38DQyg3LLesk9VSqKASv34y5A7kJBpzWkGpdH7tpump", "label": "STARMlND", "t": 17.13, "wallTs": 1782253274.19, "devHold": 1.04, "bundlers": 0, "insiders": 0, "snipers": 1.04, "top10": 1.04, "mcap": 1940, "price": null, "vol": 20.65}, {"type": "tick", "coin": "STARMlND", "mint": "H38DQyg3LLesk9VSqKASv34y5A7kJBpzWkGpdH7tpump", "label": "STARMlND", "t": 17.26, "wallTs": 1782253274.31, "devHold": 1.04, "bundlers": 0, "insiders": 0, "snipers": 1.04, "top10": 1.04, "mcap": 1940, "price": null, "vol": 20.65}, {"type": "tick", "coin": "STARMlND", "mint": "H38DQyg3LLesk9VSqKASv34y5A7kJBpzWkGpdH7tpump", "label": "STARMlND", "t": 17.38, "wallTs": 1782253274.44, "devHold": 1.04, "bundlers": 0, "insiders": 0, "snipers": 1.04, "top10": 1.04, "mcap": 1940, "price": null, "vol": 20.65}, {"type": "tick", "coin": "STARMlND", "mint": "H38DQyg3LLesk9VSqKASv34y5A7kJBpzWkGpdH7tpump", "label": "STARMlND", "t": 17.51, "wallTs": 1782253274.56, "devHold": 1.04, "bundlers": 0, "insiders": 0, "snipers": 1.04, "top10": 1.04, "mcap": 1940, "price": null, "vol": 20.65}, {"type": "tick", "coin": "STARMlND", "mint": "H38DQyg3LLesk9VSqKASv34y5A7kJBpzWkGpdH7tpump", "label": "STARMlND", "t": 17.63, "wallTs": 1782253274.69, "devHold": 1.04, "bundlers": 0, "insiders": 0, "snipers": 1.04, "top10": 1.04, "mcap": 1940, "price": null, "vol": 20.65}, {"type": "tick", "coin": "STARMlND", "mint": "H38DQyg3LLesk9VSqKASv34y5A7kJBpzWkGpdH7tpump", "label": "STARMlND", "t": 17.75, "wallTs": 1782253274.81, "devHold": 1.04, "bundlers": 0, "insiders": 0, "snipers": 1.04, "top10": 1.04, "mcap": 1940, "price": null, "vol": 20.65}, {"type": "tick", "coin": "STARMlND", "mint": "H38DQyg3LLesk9VSqKASv34y5A7kJBpzWkGpdH7tpump", "label": "STARMlND", "t": 17.87, "wallTs": 1782253274.92, "devHold": 1.04, "bundlers": 0, "insiders": 0, "snipers": 1.04, "top10": 1.04, "mcap": 1940, "price": null, "vol": 20.65}, {"type": "tick", "coin": "STARMlND", "mint": "H38DQyg3LLesk9VSqKASv34y5A7kJBpzWkGpdH7tpump", "label": "STARMlND", "t": 18.0, "wallTs": 1782253275.05, "devHold": 1.04, "bundlers": 0, "insiders": 0, "snipers": 1.04, "top10": 1.04, "mcap": 1940, "price": null, "vol": 20.65}, {"type": "tick", "coin": "STARMlND", "mint": "H38DQyg3LLesk9VSqKASv34y5A7kJBpzWkGpdH7tpump", "label": "STARMlND", "t": 18.12, "wallTs": 1782253275.17, "devHold": 1.04, "bundlers": 0, "insiders": 0, "snipers": 1.04, "top10": 1.04, "mcap": 1940, "price": null, "vol": 20.65}, {"type": "tick", "coin": "STARMlND", "mint": "H38DQyg3LLesk9VSqKASv34y5A7kJBpzWkGpdH7tpump", "label": "STARMlND", "t": 18.24, "wallTs": 1782253275.3, "devHold": 1.04, "bundlers": 0, "insiders": 0, "snipers": 1.04, "top10": 1.04, "mcap": 1940, "price": null, "vol": 20.65}, {"type": "tick", "coin": "STARMlND", "mint": "H38DQyg3LLesk9VSqKASv34y5A7kJBpzWkGpdH7tpump", "label": "STARMlND", "t": 18.37, "wallTs": 1782253275.44, "devHold": 1.04, "bundlers": 0, "insiders": 0, "snipers": 1.04, "top10": 1.04, "mcap": 1940, "price": null, "vol": 20.65}, {"type": "tick", "coin": "STARMlND", "mint": "H38DQyg3LLesk9VSqKASv34y5A7kJBpzWkGpdH7tpump", "label": "STARMlND", "t": 18.52, "wallTs": 1782253275.58, "devHold": 1.04, "bundlers": 0, "insiders": 0, "snipers": 1.04, "top10": 1.04, "mcap": 1940, "price": null, "vol": 20.65}, {"type": "tick", "coin": "STARMlND", "mint": "H38DQyg3LLesk9VSqKASv34y5A7kJBpzWkGpdH7tpump", "label": "STARMlND", "t": 18.66, "wallTs": 1782253275.71, "devHold": 1.04, "bundlers": 0, "insiders": 0, "snipers": 1.04, "top10": 1.04, "mcap": 1940, "price": null, "vol": 20.65}, {"type": "tick", "coin": "STARMlND", "mint": "H38DQyg3LLesk9VSqKASv34y5A7kJBpzWkGpdH7tpump", "label": "STARMlND", "t": 18.78, "wallTs": 1782253275.84, "devHold": 1.04, "bundlers": 0, "insiders": 0, "snipers": 1.04, "top10": 1.04, "mcap": 1940, "price": null, "vol": 20.65}, {"type": "tick", "coin": "STARMlND", "mint": "H38DQyg3LLesk9VSqKASv34y5A7kJBpzWkGpdH7tpump", "label": "STARMlND", "t": 18.9, "wallTs": 1782253275.96, "devHold": 1.04, "bundlers": 0, "insiders": 0, "snipers": 1.04, "top10": 1.04, "mcap": 1940, "price": null, "vol": 20.65}, {"type": "tick", "coin": "STARMlND", "mint": "H38DQyg3LLesk9VSqKASv34y5A7kJBpzWkGpdH7tpump", "label": "STARMlND", "t": 19.03, "wallTs": 1782253276.08, "devHold": 1.04, "bundlers": 0, "insiders": 0, "snipers": 1.04, "top10": 1.04, "mcap": 1940, "price": null, "vol": 20.65}, {"type": "tick", "coin": "STARMlND", "mint": "H38DQyg3LLesk9VSqKASv34y5A7kJBpzWkGpdH7tpump", "label": "STARMlND", "t": 19.15, "wallTs": 1782253276.21, "devHold": 1.04, "bundlers": 0, "insiders": 0, "snipers": 1.04, "top10": 1.04, "mcap": 1950, "price": null, "vol": 20.66}, {"type": "tick", "coin": "STARMlND", "mint": "H38DQyg3LLesk9VSqKASv34y5A7kJBpzWkGpdH7tpump", "label": "STARMlND", "t": 19.27, "wallTs": 1782253276.33, "devHold": 1.04, "bundlers": 0, "insiders": 0, "snipers": 1.04, "top10": 1.04, "mcap": 1950, "price": null, "vol": 20.66}, {"type": "tick", "coin": "STARMlND", "mint": "H38DQyg3LLesk9VSqKASv34y5A7kJBpzWkGpdH7tpump", "label": "STARMlND", "t": 19.4, "wallTs": 1782253276.45, "devHold": 1.04, "bundlers": 0, "insiders": 0, "snipers": 1.04, "top10": 1.04, "mcap": 1950, "price": null, "vol": 20.66}, {"type": "tick", "coin": "STARMlND", "mint": "H38DQyg3LLesk9VSqKASv34y5A7kJBpzWkGpdH7tpump", "label": "STARMlND", "t": 19.52, "wallTs": 1782253276.58, "devHold": 1.04, "bundlers": 0, "insiders": 0, "snipers": 1.04, "top10": 1.04, "mcap": 1950, "price": null, "vol": 20.66}, {"type": "tick", "coin": "STARMlND", "mint": "H38DQyg3LLesk9VSqKASv34y5A7kJBpzWkGpdH7tpump", "label": "STARMlND", "t": 19.65, "wallTs": 1782253276.7, "devHold": 1.04, "bundlers": 0, "insiders": 0, "snipers": 1.04, "top10": 1.04, "mcap": 1950, "price": null, "vol": 20.66}, {"type": "tick", "coin": "STARMlND", "mint": "H38DQyg3LLesk9VSqKASv34y5A7kJBpzWkGpdH7tpump", "label": "STARMlND", "t": 19.76, "wallTs": 1782253276.82, "devHold": 1.04, "bundlers": 0, "insiders": 0, "snipers": 1.04, "top10": 1.04, "mcap": 1950, "price": null, "vol": 20.66}, {"type": "tick", "coin": "STARMlND", "mint": "H38DQyg3LLesk9VSqKASv34y5A7kJBpzWkGpdH7tpump", "label": "STARMlND", "t": 19.88, "wallTs": 1782253276.94, "devHold": 1.04, "bundlers": 0, "insiders": 0, "snipers": 1.04, "top10": 1.04, "mcap": 1950, "price": null, "vol": 20.66}, {"type": "tick", "coin": "STARMlND", "mint": "H38DQyg3LLesk9VSqKASv34y5A7kJBpzWkGpdH7tpump", "label": "STARMlND", "t": 20.0, "wallTs": 1782253277.06, "devHold": 1.04, "bundlers": 0, "insiders": 0, "snipers": 1.04, "top10": 1.04, "mcap": 1950, "price": null, "vol": 20.66}, {"type": "tick", "coin": "STARMlND", "mint": "H38DQyg3LLesk9VSqKASv34y5A7kJBpzWkGpdH7tpump", "label": "STARMlND", "t": 20.13, "wallTs": 1782253277.19, "devHold": 1.04, "bundlers": 0, "insiders": 0, "snipers": 1.04, "top10": 1.04, "mcap": 1950, "price": null, "vol": 20.66}, {"type": "tick", "coin": "STARMlND", "mint": "H38DQyg3LLesk9VSqKASv34y5A7kJBpzWkGpdH7tpump", "label": "STARMlND", "t": 20.25, "wallTs": 1782253277.31, "devHold": 1.04, "bundlers": 0, "insiders": 0, "snipers": 1.04, "top10": 1.04, "mcap": 1950, "price": null, "vol": 20.66}, {"type": "tick", "coin": "STARMlND", "mint": "H38DQyg3LLesk9VSqKASv34y5A7kJBpzWkGpdH7tpump", "label": "STARMlND", "t": 20.37, "wallTs": 1782253277.43, "devHold": 1.04, "bundlers": 0, "insiders": 0, "snipers": 1.04, "top10": 1.04, "mcap": 1950, "price": null, "vol": 20.66}, {"type": "tick", "coin": "STARMlND", "mint": "H38DQyg3LLesk9VSqKASv34y5A7kJBpzWkGpdH7tpump", "label": "STARMlND", "t": 20.5, "wallTs": 1782253277.55, "devHold": 1.04, "bundlers": 0, "insiders": 0, "snipers": 1.04, "top10": 1.04, "mcap": 1950, "price": null, "vol": 20.66}, {"type": "tick", "coin": "STARMlND", "mint": "H38DQyg3LLesk9VSqKASv34y5A7kJBpzWkGpdH7tpump", "label": "STARMlND", "t": 20.63, "wallTs": 1782253277.68, "devHold": 1.04, "bundlers": 0, "insiders": 0, "snipers": 1.04, "top10": 1.04, "mcap": 1950, "price": null, "vol": 20.66}, {"type": "tick", "coin": "STARMlND", "mint": "H38DQyg3LLesk9VSqKASv34y5A7kJBpzWkGpdH7tpump", "label": "STARMlND", "t": 20.75, "wallTs": 1782253277.81, "devHold": 1.04, "bundlers": 0, "insiders": 0, "snipers": 1.04, "top10": 1.04, "mcap": 1950, "price": null, "vol": 20.66}], "trades": [{"amt": 0.297, "side": "buy", "mc": 1960, "trader": "", "age": 0}], "nTrades": 1}, "agents": {"volt": "STARMlND volume reading $21, mapping the curve", "prism": "profiling STARMlND \u2014 fresh deploy, 21s old, reading the meta", "sentinel": "STARMlND: dev 1% \u2192 \u00b7 bundlers 0% \u00b7 insiders 0%", "oracle": "STARMlND top10 holds 1% \u2014 spread", "hype": "STARMlND drew 1% snipers in the first seconds"}, "stats": {"coins": 127, "ticks": 24271, "rows": 26362}}